httpdatetime/__init__.py
httpdatetime/__main__.py
httpdatetime/getdatetime.py
httpdatetime/statics/httpdatetime.service
httpdatetime-1.0.2.dist-info/METADATA
httpdatetime-1.0.2.dist-info/RECORD
httpdatetime-1.0.2.dist-info/WHEEL
httpdatetime-1.0.2.dist-info/entry_points.txt
httpdatetime-1.0.2.dist-info/top_level.txt
httpdatetime-1.0.2.dist-info/zip-safe
